<?xml version='1.0' encoding='utf-8'?>
<geometry>
  <cell id="1" material="2" name="gd_fuel1_1" region="-1" universe="1" />
  <cell id="2" material="3" name="gd_fuel2_1" region="-1" universe="2" />
  <cell id="3" material="1" name="uo2_fuel1" region="-1" universe="3" />
  <cell id="4" material="5" name="gd_fuel1_2" region="1 -2" universe="1" />
  <cell id="5" material="6" name="gd_fuel2_2" region="1 -2" universe="2" />
  <cell id="6" material="4" name="uo2_fuel2" region="1 -2" universe="3" />
  <cell id="7" material="8" name="gd_fuel1_3" region="2 -3" universe="1" />
  <cell id="8" material="9" name="gd_fuel2_3" region="2 -3" universe="2" />
  <cell id="9" material="7" name="uo2_fuel3" region="2 -3" universe="3" />
  <cell id="10" material="11" name="gd_fuel1_4" region="3 -4" universe="1" />
  <cell id="11" material="12" name="gd_fuel2_4" region="3 -4" universe="2" />
  <cell id="12" material="10" name="uo2_fuel4" region="3 -4" universe="3" />
  <cell id="13" material="14" name="gd_fuel1_5" region="4 -5" universe="1" />
  <cell id="14" material="15" name="gd_fuel2_5" region="4 -5" universe="2" />
  <cell id="15" material="13" name="uo2_fuel5" region="4 -5" universe="3" />
  <cell id="16" material="17" name="gd_fuel1_6" region="5 -6" universe="1" />
  <cell id="17" material="18" name="gd_fuel2_6" region="5 -6" universe="2" />
  <cell id="18" material="16" name="uo2_fuel6" region="5 -6" universe="3" />
  <cell id="19" material="20" name="gd_fuel1_7" region="6 -7" universe="1" />
  <cell id="20" material="21" name="gd_fuel2_7" region="6 -7" universe="2" />
  <cell id="21" material="19" name="uo2_fuel7" region="6 -7" universe="3" />
  <cell id="22" material="23" name="gd_fuel1_8" region="7 -8" universe="1" />
  <cell id="23" material="24" name="gd_fuel2_8" region="7 -8" universe="2" />
  <cell id="24" material="22" name="uo2_fuel8" region="7 -8" universe="3" />
  <cell id="25" material="29" name="gd_clad1" region="8 -9" universe="1" />
  <cell id="26" material="29" name="gd_clad2" region="8 -9" universe="2" />
  <cell id="27" material="29" name="uo2_clad" region="8 -9" universe="3" />
  <cell id="28" material="30" name="gd_moderator" region="10 -11 12 -13 9" universe="1" />
  <cell id="29" material="30" name="gd_moderator" region="10 -11 12 -13 9" universe="2" />
  <cell id="30" material="30" name="uo2_moderator" region="10 -11 12 -13 9" universe="3" />
  <cell fill="4" id="31" name="assembly_cell" region="14 -15 16 -17" universe="5" />
  <lattice id="4" name="assembly">
    <pitch>1.6 1.6</pitch>
    <dimension>4 4</dimension>
    <lower_left>-3.2 -3.2</lower_left>
    <universes>
3 3 3 3 
3 3 1 3 
3 2 3 3 
3 3 3 3 </universes>
  </lattice>
  <surface coeffs="0.0 0.0 0.0625" id="1" type="z-cylinder" />
  <surface coeffs="0.0 0.0 0.125" id="2" type="z-cylinder" />
  <surface coeffs="0.0 0.0 0.1875" id="3" type="z-cylinder" />
  <surface coeffs="0.0 0.0 0.25" id="4" type="z-cylinder" />
  <surface coeffs="0.0 0.0 0.3125" id="5" type="z-cylinder" />
  <surface coeffs="0.0 0.0 0.375" id="6" type="z-cylinder" />
  <surface coeffs="0.0 0.0 0.4375" id="7" type="z-cylinder" />
  <surface coeffs="0.0 0.0 0.5" id="8" type="z-cylinder" />
  <surface coeffs="0.0 0.0 0.6" id="9" type="z-cylinder" />
  <surface coeffs="-0.8" id="10" name="minimum x" type="x-plane" />
  <surface coeffs="0.8" id="11" name="maximum x" type="x-plane" />
  <surface coeffs="-0.8" id="12" name="minimum y" type="y-plane" />
  <surface coeffs="0.8" id="13" name="maximum y" type="y-plane" />
  <surface boundary="reflective" coeffs="-3.2" id="14" name="minimum x" type="x-plane" />
  <surface boundary="reflective" coeffs="3.2" id="15" name="maximum x" type="x-plane" />
  <surface boundary="reflective" coeffs="-3.2" id="16" name="minimum y" type="y-plane" />
  <surface boundary="reflective" coeffs="3.2" id="17" name="maximum y" type="y-plane" />
</geometry>
